odoo/addons/pos_order_to_sale_order/README.rst
odoo/addons/pos_order_to_sale_order/__init__.py
odoo/addons/pos_order_to_sale_order/__manifest__.py
odoo/addons/pos_order_to_sale_order/i18n/ca.po
odoo/addons/pos_order_to_sale_order/i18n/ca_ES.po
odoo/addons/pos_order_to_sale_order/i18n/es.po
odoo/addons/pos_order_to_sale_order/i18n/fr.po
odoo/addons/pos_order_to_sale_order/i18n/it.po
odoo/addons/pos_order_to_sale_order/i18n/pos_order_to_sale_order.pot
odoo/addons/pos_order_to_sale_order/i18n/pt_BR.po
odoo/addons/pos_order_to_sale_order/models/__init__.py
odoo/addons/pos_order_to_sale_order/models/pos_config.py
odoo/addons/pos_order_to_sale_order/models/sale_order.py
odoo/addons/pos_order_to_sale_order/models/sale_order_line.py
odoo/addons/pos_order_to_sale_order/readme/CONFIGURE.rst
odoo/addons/pos_order_to_sale_order/readme/CONTRIBUTORS.rst
odoo/addons/pos_order_to_sale_order/readme/DESCRIPTION.rst
odoo/addons/pos_order_to_sale_order/readme/USAGE.rst
odoo/addons/pos_order_to_sale_order/static/description/icon.png
odoo/addons/pos_order_to_sale_order/static/description/index.html
odoo/addons/pos_order_to_sale_order/static/description/pos_config_form.png
odoo/addons/pos_order_to_sale_order/static/description/pos_frontend_buttons.png
odoo/addons/pos_order_to_sale_order/static/description/pos_frontend_order.png
odoo/addons/pos_order_to_sale_order/static/src/css/pos.css
odoo/addons/pos_order_to_sale_order/static/src/js/CreateOrderButton.js
odoo/addons/pos_order_to_sale_order/static/src/js/CreateOrderPopup.js
odoo/addons/pos_order_to_sale_order/static/src/xml/CreateOrderButton.xml
odoo/addons/pos_order_to_sale_order/static/src/xml/CreateOrderPopup.xml
odoo/addons/pos_order_to_sale_order/tests/__init__.py
odoo/addons/pos_order_to_sale_order/tests/test_pos_order_to_sale_order.py
odoo/addons/pos_order_to_sale_order/views/assets.xml
odoo/addons/pos_order_to_sale_order/views/view_pos_config.xml
odoo14_addon_pos_order_to_sale_order-14.0.1.0.2.dist-info/METADATA
odoo14_addon_pos_order_to_sale_order-14.0.1.0.2.dist-info/WHEEL
odoo14_addon_pos_order_to_sale_order-14.0.1.0.2.dist-info/top_level.txt
odoo14_addon_pos_order_to_sale_order-14.0.1.0.2.dist-info/RECORD
