Metadata-Version: 2.1
Name: odoo14-addon-pos_order_to_sale_order
Version: 14.0.1.0.2
Summary: PoS Order To Sale Order
Home-page: https://github.com/OCA/pos
Author: GRAP,Odoo Community Association (OCA)
Author-email: support@odoo-community.org
License: AGPL-3
Classifier: Programming Language :: Python
Classifier: Framework :: Odoo
Classifier: Framework :: Odoo :: 14.0
Classifier: License :: OSI Approved :: GNU Affero General Public License v3
Classifier: Development Status :: 5 - Production/Stable
Requires-Python: >=3.6
Requires-Dist: odoo<14.1dev,>=14.0a
